{
    "MoveUp": {
        "duration": 23.336999999999996,
        "start_time": 22.61,
        "fixations": {
            "Head": [
                {
                    "duration": 2.3359999999999985,
                    "start_time": 22.61,
                    "ratio": 0.10009855594120919
                },
                {
                    "duration": 0.7490000000000023,
                    "start_time": 25.945999999999998,
                    "ratio": 0.03209495650683475
                },
                {
                    "duration": 0.5,
                    "start_time": 30.697,
                    "ratio": 0.021425204610704036
                },
                {
                    "duration": 0.25,
                    "start_time": 32.696999999999996,
                    "ratio": 0.010712602305352018
                }
            ],
            "LHand": [
                {
                    "duration": 0.7490000000000023,
                    "start_time": 24.945999999999998,
                    "ratio": 0.03209495650683475
                },
                {
                    "duration": 0.0,
                    "start_time": 29.195999999999998,
                    "ratio": 0.0
                },
                {
                    "duration": 0.2519999999999989,
                    "start_time": 30.445,
                    "ratio": 0.010798303123794787
                },
                {
                    "duration": 0.7519999999999953,
                    "start_time": 31.945,
                    "ratio": 0.03222350773449867
                },
                {
                    "duration": 2.0019999999999953,
                    "start_time": 33.445,
                    "ratio": 0.08578651926125876
                },
                {
                    "duration": 0.25,
                    "start_time": 36.446,
                    "ratio": 0.010712602305352018
                }
            ],
            "RHand": [
                {
                    "duration": 0.25099999999999767,
                    "start_time": 25.695,
                    "ratio": 0.010755452714573326
                },
                {
                    "duration": 0.75,
                    "start_time": 26.695,
                    "ratio": 0.032137806916056055
                },
                {
                    "duration": 0.4989999999999988,
                    "start_time": 27.947,
                    "ratio": 0.021382354201482576
                },
                {
                    "duration": 0.75,
                    "start_time": 29.195999999999998,
                    "ratio": 0.032137806916056055
                },
                {
                    "duration": 0.2480000000000011,
                    "start_time": 30.197,
                    "ratio": 0.010626901486909248
                },
                {
                    "duration": 0.7480000000000011,
                    "start_time": 31.197,
                    "ratio": 0.03205210609761328
                },
                {
                    "duration": 0.49800000000000466,
                    "start_time": 32.946999999999996,
                    "ratio": 0.02133950379226142
                },
                {
                    "duration": 0.9990000000000023,
                    "start_time": 35.446999999999996,
                    "ratio": 0.042807558812186765
                },
                {
                    "duration": 0.9990000000000023,
                    "start_time": 36.696,
                    "ratio": 0.042807558812186765
                }
            ],
            "Object": [
                {
                    "duration": 4.000999999999991,
                    "start_time": 41.946000000000005,
                    "ratio": 0.1714444872948533
                }
            ],
            "VisualServoing": [
                {
                    "duration": 0.75,
                    "start_time": 28.445999999999998,
                    "ratio": 0.032137806916056055
                },
                {
                    "duration": 0.2510000000000012,
                    "start_time": 29.945999999999998,
                    "ratio": 0.010755452714573479
                },
                {
                    "duration": 4.251000000000005,
                    "start_time": 37.695,
                    "ratio": 0.1821570896002059
                }
            ]
        }
    },
    "MoveDown": {
        "duration": 13.061000000000007,
        "start_time": 45.946999999999996,
        "fixations": {
            "Object": [
                {
                    "duration": 1.75,
                    "start_time": 45.946999999999996,
                    "ratio": 0.13398667789602628
                }
            ],
            "LHand": [
                {
                    "duration": 2.25,
                    "start_time": 47.696999999999996,
                    "ratio": 0.1722685858663195
                },
                {
                    "duration": 1.4990000000000094,
                    "start_time": 50.446999999999996,
                    "ratio": 0.11476916009493979
                },
                {
                    "duration": 1.0010000000000048,
                    "start_time": 52.945,
                    "ratio": 0.07664037975652739
                },
                {
                    "duration": 0.25199999999999534,
                    "start_time": 54.945,
                    "ratio": 0.019294081617027427
                },
                {
                    "duration": 0.49900000000000944,
                    "start_time": 56.446999999999996,
                    "ratio": 0.03820534415435335
                },
                {
                    "duration": 0.9980000000000047,
                    "start_time": 57.196999999999996,
                    "ratio": 0.07641068830870562
                }
            ],
            "RHand": [
                {
                    "duration": 0.5,
                    "start_time": 49.946999999999996,
                    "ratio": 0.03828190797029322
                },
                {
                    "duration": 0.9989999999999952,
                    "start_time": 51.946000000000005,
                    "ratio": 0.07648725212464548
                },
                {
                    "duration": 0.9989999999999952,
                    "start_time": 53.946000000000005,
                    "ratio": 0.07648725212464548
                },
                {
                    "duration": 1.25,
                    "start_time": 55.196999999999996,
                    "ratio": 0.09570476992573304
                },
                {
                    "duration": 0.25099999999999056,
                    "start_time": 56.946000000000005,
                    "ratio": 0.019217517801086475
                }
            ],
            "VisualServoing": [
                {
                    "duration": 0.06199999999999761,
                    "start_time": 58.946000000000005,
                    "ratio": 0.004746956588316176
                }
            ],
            "Torso": [
                {
                    "duration": 0.24900000000000944,
                    "start_time": 58.696999999999996,
                    "ratio": 0.019064390169206746
                }
            ]
        }
    },
    "Move": {
        "duration": 6.893999999999998,
        "start_time": 59.008,
        "fixations": {
            "VisualServoing": [
                {
                    "duration": 0.47399999999999665,
                    "start_time": 59.008,
                    "ratio": 0.0687554395126192
                }
            ],
            "Direction": [
                {
                    "duration": 3.2510000000000048,
                    "start_time": 59.482,
                    "ratio": 0.4715694807078627
                }
            ],
            "LHand": [
                {
                    "duration": 0.9979999999999976,
                    "start_time": 62.733000000000004,
                    "ratio": 0.14476356251813138
                }
            ],
            "Torso": [
                {
                    "duration": 2.1709999999999994,
                    "start_time": 63.731,
                    "ratio": 0.3149115172613867
                }
            ]
        }
    },
    "Regrasp": {
        "duration": 25.092,
        "start_time": 65.902,
        "fixations": {
            "Torso": [
                {
                    "duration": 1.8349999999999937,
                    "start_time": 65.902,
                    "ratio": 0.07313087836760696
                },
                {
                    "duration": 1.5,
                    "start_time": 77.987,
                    "ratio": 0.059780009564801534
                },
                {
                    "duration": 0.25099999999999056,
                    "start_time": 80.236,
                    "ratio": 0.010003188267176414
                },
                {
                    "duration": 0.2510000000000048,
                    "start_time": 90.236,
                    "ratio": 0.01000318826717698
                }
            ],
            "LHand": [
                {
                    "duration": 2.5,
                    "start_time": 67.737,
                    "ratio": 0.09963334927466923
                },
                {
                    "duration": 0.5009999999999906,
                    "start_time": 74.736,
                    "ratio": 0.019966523194643336
                },
                {
                    "duration": 0.7509999999999906,
                    "start_time": 77.236,
                    "ratio": 0.02992985812211026
                },
                {
                    "duration": 0.24899999999999523,
                    "start_time": 82.48700000000001,
                    "ratio": 0.009923481587756864
                }
            ],
            "RHand": [
                {
                    "duration": 0.5069999999999908,
                    "start_time": 90.48700000000001,
                    "ratio": 0.02020564323290255
                }
            ],
            "Direction": [
                {
                    "duration": 1.2510000000000048,
                    "start_time": 81.236,
                    "ratio": 0.04985652797704467
                },
                {
                    "duration": 5.25,
                    "start_time": 83.98700000000001,
                    "ratio": 0.20923003347680535
                }
            ],
            "Head": [
                {
                    "duration": 0.7510000000000048,
                    "start_time": 82.736,
                    "ratio": 0.029929858122110825
                }
            ]
        }
    },
    "Place": {
        "duration": 41.197,
        "start_time": 90.994,
        "fixations": {
            "RHand": [
                {
                    "duration": 0.4939999999999998,
                    "start_time": 90.994,
                    "ratio": 0.011991164405175128
                },
                {
                    "duration": 0.5010000000000048,
                    "start_time": 92.54299999999999,
                    "ratio": 0.012161079690268825
                },
                {
                    "duration": 1.5010000000000048,
                    "start_time": 93.54299999999999,
                    "ratio": 0.03643469184649379
                },
                {
                    "duration": 1.0010000000000048,
                    "start_time": 96.04299999999999,
                    "ratio": 0.024297885768381308
                },
                {
                    "duration": 4.0,
                    "start_time": 98.044,
                    "ratio": 0.09709444862489987
                },
                {
                    "duration": 0.5010000000000048,
                    "start_time": 106.79299999999999,
                    "ratio": 0.012161079690268825
                },
                {
                    "duration": 3.75,
                    "start_time": 109.294,
                    "ratio": 0.09102604558584362
                },
                {
                    "duration": 2.4989999999999952,
                    "start_time": 116.794,
                    "ratio": 0.06065975677840608
                },
                {
                    "duration": 3.8980000000000103,
                    "start_time": 119.29299999999999,
                    "ratio": 0.09461854018496517
                },
                {
                    "duration": 0.2510000000000048,
                    "start_time": 123.191,
                    "ratio": 0.006092676651212582
                },
                {
                    "duration": 0.2510000000000048,
                    "start_time": 130.441,
                    "ratio": 0.006092676651212582
                }
            ],
            "Torso": [
                {
                    "duration": 1.4989999999999952,
                    "start_time": 130.692,
                    "ratio": 0.03638614462218111
                }
            ],
            "VisualServoing": [
                {
                    "duration": 0.4989999999999952,
                    "start_time": 93.044,
                    "ratio": 0.012112532465956142
                },
                {
                    "duration": 0.9989999999999952,
                    "start_time": 95.044,
                    "ratio": 0.024249338544068626
                },
                {
                    "duration": 1.0,
                    "start_time": 97.044,
                    "ratio": 0.024273612156224967
                },
                {
                    "duration": 4.248999999999995,
                    "start_time": 102.044,
                    "ratio": 0.10313857805179977
                }
            ],
            "Head": [
                {
                    "duration": 1.75,
                    "start_time": 107.294,
                    "ratio": 0.04247882127339369
                },
                {
                    "duration": 0.25,
                    "start_time": 109.044,
                    "ratio": 0.006068403039056242
                },
                {
                    "duration": 3.75,
                    "start_time": 113.044,
                    "ratio": 0.09102604558584362
                },
                {
                    "duration": 6.998999999999995,
                    "start_time": 123.44200000000001,
                    "ratio": 0.1698910114814184
                }
            ]
        }
    }
}